bezierfit/__about__.py
bezierfit/__init__.py
bezierfit-0.0.1a1.dev1.dist-info/METADATA
bezierfit-0.0.1a1.dev1.dist-info/WHEEL
bezierfit-0.0.1a1.dev1.dist-info/licenses/LICENSE.txt
bezierfit-0.0.1a1.dev1.dist-info/RECORD
