Metadata-Version: 2.3
Name: bezierfit
Version: 0.0.1a1.dev1
Project-URL: Documentation, https://github.com/Sergiu Deitsch/bezierfit#readme
Project-URL: Issues, https://github.com/Sergiu Deitsch/bezierfit/issues
Project-URL: Source, https://github.com/Sergiu Deitsch/bezierfit
Author-email: Sergiu Deitsch <sergiu.deitsch@gmail.com>
License: Apache-2.0
Classifier: Development Status :: 3 - Alpha
Classifier: Programming Language :: Python
Classifier: Programming Language :: Python :: 3.8
Classifier: Programming Language :: Python :: 3.9
Classifier: Programming Language :: Python :: 3.10
Classifier: Programming Language :: Python :: 3.11
Classifier: Programming Language :: Python :: 3.12
Classifier: Programming Language :: Python :: Implementation :: CPython
Classifier: Programming Language :: Python :: Implementation :: PyPy
Requires-Python: >=3.8
